[{"footer-area-1":["custom_html-4"],"footer-area-2":["custom_html-3"],"footer-area-3":["custom_html-2"]},{"custom_html":{"4":{"title":"","content":"<div style=\"padding-right: 20%;\">\r\n<h5>Contact us<br \/>\r\nCurabitur et ligula molestie ultricies porta urna. <\/h5>\r\n[divider height=\"20\"]\r\n[button title=\"Read more\" link=\"https:\/\/themes.muffingroup.com\/be\/farm2\/contact\/\" target=\"_blank\" align=\"\" icon=\"\" icon_position=\"\" color=\"theme\" font_color=\"#fff\" size=\"2\" full_width=\"\" class=\"\" download=\"\" rel=\"\"]\r\n[divider height=\"30\"]\r\n<p>\r\n<a href=\"#\" style=\"margin-right: 15px;\">FAQ<\/a>\r\n<a href=\"#\" style=\"margin-right: 15px;\">Support<\/a>\r\n<a href=\"#\" style=\"margin-right: 15px;\">Useful info<\/a>\r\n<\/p>\r\n<\/div>"},"3":{"title":"","content":"<div style=\"padding-right: 20%;\">\r\n<h5>Ullamcorper<\/h5>\r\n[divider height=\"10\"]\r\n<ul class=\"list_custom\">\t\r\n<li>[icon type=\"icon-dot\" color=\"#5e9b50\"]Lorem ipsum dolor sit amet enim. \r\nEtiam ullamcorper<\/li>\r\n<li>[icon type=\"icon-dot\" color=\"#5e9b50\"]Maecenas malesuada elit lectus felis ultricies <\/li>\r\n<li>[icon type=\"icon-dot\" color=\"#5e9b50\"]Curabitur ligula<\/li>\r\n<li>[icon type=\"icon-dot\" color=\"#5e9b50\"]Vestibulum<\/li>\r\n<\/ul>\r\n<\/div>"},"2":{"title":"","content":"<div style=\"padding-right: 20%;\">\r\n<h5>Our mission<\/h5>\r\n[divider height=\"10\"]\r\n<p>Lorem ipsum dolor sit amet enim. Etiam ullamcorper. Suspendisse a pellentesque dui, non felis. Maecenas malesuada elit lectus felis, malesuada ultricies. Curabitur et ligula. Ut molestie enim.<\/p>\r\n<a href=\"#\">Read more<\/a>\r\n<\/div>"},"_multiwidget":1}}]